humba/__init__.py
humba/core.py
humba/jits.py
humba-0.1a5.dist-info/LICENSE
humba-0.1a5.dist-info/METADATA
humba-0.1a5.dist-info/WHEEL
humba-0.1a5.dist-info/top_level.txt
humba-0.1a5.dist-info/RECORD
