Metadata-Version: 2.1
Name: humba
Version: 0.1a5
Summary: Histogramming using numba
Home-page: https://github.com/douglasdavis/humba
Author: Doug Davis
Author-email: ddavis@ddavis.io
Maintainer: Doug Davis
Maintainer-email: ddavis@ddavis.io
License: BSD 3-clause
Platform: UNKNOWN
Classifier: Development Status :: 3 - Alpha
Classifier: Intended Audience :: Science/Research
Classifier: Programming Language :: Python :: 3.6
Classifier: Programming Language :: Python :: 3.7
Requires-Python: >=3.6
Requires-Dist: numpy (>=1.12)
Requires-Dist: numba (>=0.42)
